{"name":"浏览器原理","slug":"浏览器原理","count":1,"postlist":[{"title":"前端基础-性能优化1","uid":"efb20c5240686fa74a28eb245753ea20","slug":"2022-05-12performance","date":"2022-05-12T10:27:05.000Z","updated":"2023-02-20T21:20:56.459Z","comments":true,"path":"api/articles/2022-05-12performance.json","keywords":null,"cover":[],"text":"优化的指标 白屏时间 &#x3D; 地址栏输入网址后回车 - 浏览器出现第一个元素 首屏时间 &#x3D; 地址栏输入网址后回车 - 浏览器第一屏渲染完成 影响白屏时间的因素：网络，服务端性能，前端页面结构设计。 影响首屏时间的因素：白屏时间，资源下载执行时间。 通常在 head...","link":"","photos":[],"count_time":{"symbolsCount":"34k","symbolsTime":"31 mins."},"categories":[{"name":"性能优化","slug":"性能优化","count":9,"path":"api/categories/性能优化.json"}],"tags":[{"name":"前端基础","slug":"前端基础","count":55,"path":"api/tags/前端基础.json"},{"name":"性能优化","slug":"性能优化","count":9,"path":"api/tags/性能优化.json"},{"name":"浏览器原理","slug":"浏览器原理","count":1,"path":"api/tags/浏览器原理.json"}],"author":{"name":"举手摘月亮","slug":"blog-author","avatar":"http://t-blog-images.aijs.top/img/202303171118970.webp","link":"/","description":"<div><p>眼中有光，心中有梦，脚下有路</p><div>","socials":{"github":"https://github.com/841660202","twitter":"","stackoverflow":"","wechat":"","qq":"","weibo":"","zhihu":"","csdn":"https://blog.csdn.net/web_longboss","juejin":"","customs":{}}}}]}